Workbook
Name Slicer_Month1: #N/A
Name Slicer_Product_Category: #N/A
Name Slicer_Region1: #N/A

Sheet Sales_Rep_Info
A1: Sales_Rep | B1: Region | C1: Hire_Date | D1: Commission_Rate | E1: Days_since_hire
A2: JohnSmith | B2: North | C2: 44635 | D2: 0.08 | E2: 1428
A3: EmmaDavis | B3: South | C3: 44397 | D3: 0.09 | E3: 1666
A4: CarlosLee | B4: East | C4: 44936 | D4: 0.07 | E4: 1127
A5: SarahChen | B5: West | C5: 44870 | D5: 0.08 | E5: 1193

Sheet Expenses
A1: Month | B1: Department | C1: Expense_Category | D1: Amount
A2: January | B2: Sales | C2: Marketing | D2: 8500
A3: January | B3: Sales | C3: Travel | D3: 4200
A4: January | B4: Operations | C4: Rent | D4: 12000
A5: January | B5: Operations | C5: Utilities | D5: 2800
A6: January | B6: HR | C6: Salaries | D6: 45000
A7: January | B7: HR | C7: Training | D7: 3500
A8: February | B8: Sales | C8: Marketing | D8: 9200
A9: February | B9: Sales | C9: Travel | D9: 3800
A10: February | B10: Operations | C10: Rent | D10: 12000
A11: February | B11: Operations | C11: Utilities | D11: 2600
A12: February | B12: HR | C12: Salaries | D12: 45000
A13: February | B13: HR | C13: Training | D13: 4200
... A19: March | B19: HR | C19: Training | D19: 3800

Sheet Sales_Targets
A1: Region | B1: Month | C1: Target_Revenue | D1: Category
A2: North | B2: January | C2: 15000 | D2: Electronics
A3: North | B3: January | C3: 8000 | D3: Furniture
A4: North | B4: January | C4: 3000 | D4: OfficeSupplies
A5: South | B5: January | C5: 12000 | D5: Electronics
A6: South | B6: January | C6: 6000 | D6: Furniture
A7: South | B7: January | C7: 2500 | D7: OfficeSupplies
A8: East | B8: January | C8: 14000 | D8: Electronics
A9: East | B9: January | C9: 7000 | D9: Furniture
A10: East | B10: January | C10: 2800 | D10: OfficeSupplies
A11: West | B11: January | C11: 13000 | D11: Electronics
A12: West | B12: January | C12: 6500 | D12: Furniture
A13: West | B13: January | C13: 2600 | D13: OfficeSupplies
... A36: West | B36: March | C36: 7865 | D36: Furniture
A37: West | B37: March | D37: OfficeSupplies

Sheet Revenue_Analysis
B3: Column Labels
B4: January | E4: February | H4: March | K4: Total Sum of Total_Revenue | L4: Total Sum of ProfitMargin | M4: Total Sum of Revenue_vs_Target%
A5: Row Labels | B5: Sum of Total_Revenue | C5: Sum of ProfitMargin | D5: Sum of Revenue_vs_Target% | E5: Sum of Total_Revenue | F5: Sum of ProfitMargin | G5: Sum of Revenue_vs_Target% | H5: Sum of Total_Revenue | I5: Sum of ProfitMargin | J5: Sum of Revenue_vs_Target%
A6: East | B6: 4050 | C6: 89 | D6: 0.225 | E6: 8300 | F6: 121 | G6: 0.21842105 | H6: 1700 | I6: 51 | J6: 0.56666667 | K6: 14050 | L6: 261 | M6: 0.23813559
A7: Electronics | B7: 2800 | C7: 37 | D7: 0.18666667 | E7: 5600 | F7: 74 | G7: 0.18666667 | J7: #DIV/0! | K7: 8400 | L7: 111 | M7: 0.18666667
A8: Furniture | D8: #DIV/0! | E8: 2700 | F8: 47 | G8: 0.3375 | J8: #DIV/0! | K8: 2700 | L8: 47 | M8: 0.3375
A9: OfficeSupplies | B9: 1250 | C9: 52 | D9: 0.41666667 | G9: #DIV/0! | H9: 1700 | I9: 51 | J9: 0.56666667 | K9: 2950 | L9: 103 | M9: 0.49166667
A10: North | B10: 16560 | C10: 105 | D10: 0.43578947 | E10: 1340 | F10: 96 | G10: 0.22333333 | H10: 14040 | I10: 76 | J10: 0.61043478 | K10: 31940 | L10: 277 | M10: 0.47671642
A11: Electronics | B11: 14400 | C11: 58 | D11: 0.48 | G11: #DIV/0! | H11: 10800 | I11: 29 | J11: 0.72 | K11: 25200 | L11: 87 | M11: 0.56
A12: Furniture | B12: 2160 | C12: 47 | D12: 0.27 | G12: #DIV/0! | H12: 3240 | I12: 47 | J12: 0.405 | K12: 5400 | L12: 94 | M12: 0.3375
A13: OfficeSupplies | D13: #DIV/0! | E13: 1340 | F13: 96 | G13: 0.22333333 | J13: #DIV/0! | K13: 1340 | L13: 96 | M13: 0.22333333
A14: South | B14: 5925 | C14: 120 | D14: 0.22788462 | E14: 7280 | F14: 65 | G14: 0.31652174 | H14: 3150 | I14: 38 | J14: 0.39375 | K14: 16355 | L14: 223 | M14: 0.28692982
A15: Electronics | B15: 3300 | C15: 31 | D15: 0.22 | E15: 4800 | F15: 29 | G15: 0.32 | J15: #DIV/0! | K15: 8100 | L15: 60 | M15: 0.27
A16: Furniture | B16: 1350 | C16: 38 | D16: 0.16875 | E16: 2480 | F16: 36 | G16: 0.31 | H16: 3150 | I16: 38 | J16: 0.39375 | K16: 6980 | L16: 112 | M16: 0.29083333
A17: OfficeSupplies | B17: 1275 | C17: 51 | D17: 0.425 | G17: #DIV/0! | J17: #DIV/0! | K17: 1275 | L17: 51 | M17: 0.425
A18: West | B18: 2360 | C18: 72 | D18: 0.21454545 | E18: 8150 | F18: 121 | G18: 0.31346154 | H18: 2750 | I18: 31 | J18: 0.18333333 | K18: 13260 | L18: 224 | M18: 0.255
A19: Electronics | D19: #DIV/0! | E19: 4400 | F19: 31 | G19: 0.29333333 | H19: 2750 | I19: 31 | J19: 0.18333333 | K19: 7150 | L19: 62 | M19: 0.23833333
A20: Furniture | B20: 1240 | C20: 36 | D20: 0.155 | E20: 2250 | F20: 38 | G20: 0.28125 | J20: #DIV/0! | K20: 3490 | L20: 74 | M20: 0.218125
A21: OfficeSupplies | B21: 1120 | C21: 36 | D21: 0.37333333 | E21: 1500 | F21: 52 | G21: 0.5 | J21: #DIV/0! | K21: 2620 | L21: 88 | M21: 0.43666667
A22: Grand Total | B22: 28895 | C22: 386 | D22: 0.31069892 | E22: 25070 | F22: 403 | G22: 0.26956989 | H22: 21640 | I22: 196 | J22: 0.44163265 | K22: 75605 | L22: 985 | M22: 0.3217234

Sheet Sales_Rep_Performance
A3: Row Labels | B3: Sum of Total_Revenue | C3: Count of Sales_Rep | D3: Sum of Commission_Amount
A4: JohnSmith | B4: 31940 | C4: 7 | D4: 2555.2
A5: EmmaDavis | B5: 16355 | C5: 6 | D5: 1471.95
A6: CarlosLee | B6: 14050 | C6: 6 | D6: 983.5
A7: SarahChen | B7: 13260 | C7: 6 | D7: 1060.8
A8: Grand Total | B8: 75605 | C8: 25 | D8: 6071.45

Sheet Product_Performance
A3: Row Labels | B3: Sum of Units_Sold | C3: Sum of Profit
A4: Electronics | B4: 68 | C4: 15100
A5: Laptop | B5: 25 | C5: 8750
A6: Monitor | B6: 24 | C6: 3120
A7: Tablet | B7: 19 | C7: 3230
A8: Furniture | B8: 66 | C8: 7725
A9: Cabinet | B9: 6 | C9: 1350
A10: Chair | B10: 45 | C10: 3825
A11: Desk | B11: 15 | C11: 2550
A12: OfficeSupplies | B12: 252 | C12: 3935
A13: Paper | B13: 110 | C13: 1430
A14: Pens | B14: 100 | C14: 300
A15: Printer | B15: 7 | C15: 700
... A17: Grand Total | B17: 386 | C17: 26760

Sheet Dashboard
A1: Region | B1: Year | C1: Total Revenue (YTD) | D1: Total Profit (YTD) | E1: Avg Profit Margin | F1: No of Transactions
A2: South | B2: 2024 | C2: =SUMIFS(Sales_Data!$H:$H,Sales_Data!$L:$L,Dashboard!B2,Sales_Data!$B:$B,Dashboard!A2) -> 16355 | D2: =SUMIFS(Sales_Data!$J:$J,Sales_Data!$B:$B,Dashboard!A2,Sales_Data!$L:$L,Dashboard!B2) -> 5665 | E2: =ROUND(AVERAGEIFS(Sales_Data!$N:$N,Sales_Data!$B:$B,Dashboard!A2,Sales_Data!$L:$L,Dashboard!B2),2) -> 37.17 | F2: =COUNTIFS(Sales_Data!$B:$B, Dashboard!A2,Sales_Data!L:L,Dashboard!B2) -> 6
A3: North | B3: 2024 | C3: =SUMIFS(Sales_Data!$H:$H,Sales_Data!$L:$L,Dashboard!B3,Sales_Data!$B:$B,Dashboard!A3) -> 31940 | D3: =SUMIFS(Sales_Data!$J:$J,Sales_Data!$B:$B,Dashboard!A3,Sales_Data!$L:$L,Dashboard!B3) -> 10500 | E3: =ROUND(AVERAGEIFS(Sales_Data!$N:$N,Sales_Data!$B:$B,Dashboard!A3,Sales_Data!$L:$L,Dashboard!B3),2) -> 39.57 | F3: =COUNTIFS(Sales_Data!$B:$B, Dashboard!A3,Sales_Data!L:L,Dashboard!B3) -> 7
A4: East | B4: 2024 | C4: =SUMIFS(Sales_Data!$H:$H,Sales_Data!$L:$L,Dashboard!B4,Sales_Data!$B:$B,Dashboard!A4) -> 14050 | D4: =SUMIFS(Sales_Data!$J:$J,Sales_Data!$B:$B,Dashboard!A4,Sales_Data!$L:$L,Dashboard!B4) -> 5905 | E4: =ROUND(AVERAGEIFS(Sales_Data!$N:$N,Sales_Data!$B:$B,Dashboard!A4,Sales_Data!$L:$L,Dashboard!B4),2) -> 43.5 | F4: =COUNTIFS(Sales_Data!$B:$B, Dashboard!A4,Sales_Data!L:L,Dashboard!B4) -> 6
A5: East | B5: 2024 | C5: =SUMIFS(Sales_Data!$H:$H,Sales_Data!$L:$L,Dashboard!B5,Sales_Data!$B:$B,Dashboard!A5) -> 14050 | D5: =SUMIFS(Sales_Data!$J:$J,Sales_Data!$B:$B,Dashboard!A5,Sales_Data!$L:$L,Dashboard!B5) -> 5905 | E5: =ROUND(AVERAGEIFS(Sales_Data!$N:$N,Sales_Data!$B:$B,Dashboard!A5,Sales_Data!$L:$L,Dashboard!B5),2) -> 43.5 | F5: =COUNTIFS(Sales_Data!$B:$B, Dashboard!A5,Sales_Data!L:L,Dashboard!B5) -> 6
A6: Total | C6: =SUM(C2:C5) -> 76395 | D6: =SUM(D2:D5) -> 27975 | E6: =SUM(E2:E5) -> 163.74 | F6: =SUM(F2:F5) -> 25

Sheet Visualizations
A3: Sum of Target_Revenue | B3: Column Labels
A4: Row Labels | B4: January | C4: February | D4: March | E4: Grand Total
A5: East | B5: 18000 | C5: 38000 | D5: 3000 | E5: 59000
A6: North | B6: 38000 | C6: 6000 | D6: 23000 | E6: 67000
A7: South | B7: 26000 | C7: 23000 | D7: 8000 | E7: 57000
A8: West | B8: 11000 | C8: 26000 | D8: 15000 | E8: 52000
A9: Grand Total | B9: 93000 | C9: 93000 | D9: 49000 | E9: 235000
A11: Row Labels | B11: Sum of Total_Revenue | C11: Sum of Commission-Amount | D11: Count of Sales_Rep
A12: CarlosLee | B12: 14050 | C12: 983.5 | D12: 6
A13: EmmaDavis | B13: 16355 | C13: 1471.95 | D13: 6
A14: JohnSmith | B14: 31940 | C14: 2555.2 | D14: 7
A15: SarahChen | B15: 13260 | C15: 1060.8 | D15: 6
A16: Grand Total | B16: 75605 | C16: 6071.45 | D16: 25
D17: Row Labels | E17: Sum of Total_Revenue
A18: Row Labels | B18: Sum of Profit | D18: Electronics | E18: 48850
A19: January | B19: 9935 | D19: Furniture | E19: 18570
A20: February | B20: 9245 | D20: OfficeSupplies | E20: 8185
A21: March | B21: 7580 | D21: Grand Total | E21: 75605
A22: Grand Total | B22: 26760

Sheet Scenario Summary
B2: Scenario Summary
D3: Current Values: | E3: Best | F3: Worst | G3: Most likely
E4: Created by PIJUSH PANDIT on 12-02-2026 | F4: Created by PIJUSH PANDIT on 12-02-2026 | G4: Created by PIJUSH PANDIT on 12-02-2026
B5: Changing Cells:
C6: $H$2 | D6: 1200 | E6: 0.2 | F6: -0.15 | G6: 0.1
C7: $G$2 | D7: 5 | E7: 0.05 | F7: -0.1 | G7: 0
B8: Result Cells:
C9: $L$4 | D9: 50000 | E9: 44000.01 | F9: 44000.015 | G9: 44000
C10: $M$4 | D10: 50000 | E10: 50000 | F10: 50000 | G10: 50000
C11: $N$4 | D11: 50000 | E11: 50000 | F11: 50000 | G11: 50000
B12: Notes: Current Values column represents values of changing cells at
B13: time Scenario Summary Report was created. Changing cells for each
B14: scenario are highlighted in gray.

Sheet What if analysis
A1: Date | B1: Month | C1: Region | D1: Product_Category | E1: Product | F1: Sales_Rep | G1: Units_Sold | H1: Unit_Price | I1: Total_Revenue | J1: Cost_Per_Unit | L1: Goal Seek
A2: 45296 | B2: =TEXT(A2,"mmm") -> Jan | C2: North | D2: Electronics | E2: Laptop | F2: John Smith | G2: 5 | H2: 1200 | I2: =G2*H2 -> 6000 | J2: 850 | L2: Monthly Revenue
A3: 45299 | B3: =TEXT(A3,"mmm") -> Jan | C3: South | D3: Furniture | E3: Desk | F3: Emma Davis | G3: 3 | H3: 450 | I3: =G3*H3 -> 1350 | J3: 280 | L3: Jan | M3: Feb | N3: Mar
A4: 45301 | B4: =TEXT(A4,"mmm") -> Jan | C4: East | D4: Electronics | E4: Monitor | F4: Carlos Lee | G4: 8 | H4: 350 | I4: =G4*H4 -> 2800 | J4: 220 | L4: =SUMIFS($I:$I,$B:$B,B2) -> 50000 | M4: =SUMIFS($I:$I,$B:$B,B12) -> 50000 | N4: =SUMIFS($I:$I,$B:$B,B22) -> 50000
A5: 45303 | B5: =TEXT(A5,"mmm") -> Jan | C5: West | D5: Office Supplies | E5: Printer | F5: Sarah Chen | G5: 4 | H5: 280 | I5: =G5*H5 -> 1120 | J5: 180
A6: 45306 | B6: =TEXT(A6,"mmm") -> Jan | C6: North | D6: Furniture | E6: Chair | F6: John Smith | G6: 12 | H6: 180 | I6: =G6*H6 -> 2160 | J6: 95 | L6: Data Table
A7: 45309 | B7: =TEXT(A7,"mmm") -> Jan | C7: South | D7: Electronics | E7: Tablet | F7: Emma Davis | G7: 6 | H7: 550 | I7: =G7*H7 -> 3300 | J7: 380 | L7: Date | M7: Product | N7: Volumn | O7: Unit Price | P7: Revenue | Q7: Profit
A8: 45311 | B8: =TEXT(A8,"mmm") -> Jan | C8: East | D8: Office Supplies | E8: Paper | F8: Carlos Lee | G8: 50 | H8: 447.1 | I8: =G8*H8 -> 22355 | J8: 12 | L8: 45296 | M8: Laptop | N8: 5 | O8: 1200 | P8: =O8*N8 -> 6000 | Q8: =P8-(J2*G2) -> 1750
A9: 45313 | B9: =TEXT(A9,"mmm") -> Jan | C9: West | D9: Furniture | E9: Cabinet | F9: Sarah Chen | G9: 2 | H9: 620 | I9: =G9*H9 -> 1240 | J9: 395
A10: 45316 | B10: =TEXT(A10,"mmm") -> Jan | C10: North | D10: Electronics | E10: Laptop | F10: John Smith | G10: 7 | H10: 1200 | I10: =G10*H10 -> 8400 | J10: 850 | L10: How profit changes with volumn and price
A11: 45319 | B11: =TEXT(A11,"mmm") -> Jan | C11: South | D11: Office Supplies | E11: Toner | F11: Emma Davis | G11: 15 | H11: 85 | I11: =G11*H11 -> 1275 | J11: 42 | L11: =Q8 -> 1750 | M11: 1200 | N11: 1400 | O11: 1600 | P11: 1800 | Q11: 2000
A12: 45324 | B12: =TEXT(A12,"mmm") -> Feb | C12: East | D12: Electronics | E12: Monitor | F12: Carlos Lee | G12: 10 | H12: 350 | I12: =G12*H12 -> 3500 | J12: 220 | L12: 5 | M12: 1750 | N12: 2750 | O12: 3750 | P12: 4750 | Q12: 5750
A13: 45327 | B13: =TEXT(A13,"mmm") -> Feb | C13: West | D13: Furniture | E13: Desk | F13: Sarah Chen | G13: 5 | H13: 450 | I13: =G13*H13 -> 2250 | J13: 280 | L13: 10 | M13: 7750 | N13: 9750 | O13: 11750 | P13: 13750 | Q13: 15750
A14: 45330 | B14: =TEXT(A14,"mmm") -> Feb | C14: North | D14: Office Supplies | E14: Pens | F14: John Smith | G14: 100 | H14: 5 | I14: =G14*H14 -> 500 | J14: 2 | L14: 15 | M14: 13750 | N14: 16750 | O14: 19750 | P14: 22750 | Q14: 25750
A15: 45332 | B15: =TEXT(A15,"mmm") -> Feb | C15: South | D15: Electronics | E15: Laptop | F15: Emma Davis | G15: 4 | H15: 1200 | I15: =G15*H15 -> 4800 | J15: 850 | L15: 20 | M15: 19750 | N15: 23750 | O15: 27750 | P15: 31750 | Q15: 35750
A16: 45334 | B16: =TEXT(A16,"mmm") -> Feb | C16: East | D16: Furniture | E16: Chair | F16: Carlos Lee | G16: 15 | H16: 180 | I16: =G16*H16 -> 2700 | J16: 95 | L16: 25 | M16: 25750 | N16: 30750 | O16: 35750 | P16: 40750 | Q16: 45750
A17: 45337 | B17: =TEXT(A17,"mmm") -> Feb | C17: West | D17: Electronics | E17: Tablet | F17: Sarah Chen | G17: 8 | H17: 550 | I17: =G17*H17 -> 4400 | J17: 380
A18: 45340 | B18: =TEXT(A18,"mmm") -> Feb | C18: North | D18: Office Supplies | E18: Printer | F18: John Smith | G18: 3 | H18: 280 | I18: =G18*H18 -> 840 | J18: 180
A19: 45342 | B19: =TEXT(A19,"mmm") -> Feb | C19: South | D19: Furniture | E19: Cabinet | F19: Emma Davis | G19: 4 | H19: 620 | I19: =G19*H19 -> 2480 | J19: 395
A20: 45344 | B20: =TEXT(A20,"mmm") -> Feb | C20: East | D20: Electronics | E20: Monitor | F20: Carlos Lee | G20: 6 | H20: 4505 | I20: =G20*H20 -> 27030 | J20: 220
A21: 45347 | B21: =TEXT(A21,"mmm") -> Feb | C21: West | D21: Office Supplies | E21: Paper | F21: Sarah Chen | G21: 60 | H21: 25 | I21: =G21*H21 -> 1500 | J21: 12
A22: 45352 | B22: =TEXT(A22,"mmm") -> Mar | C22: North | D22: Electronics | E22: Laptop | F22: John Smith | G22: 9 | H22: 4351.1111 | I22: =G22*H22 -> 39160 | J22: 850
A23: 45356 | B23: =TEXT(A23,"mmm") -> Mar | C23: South | D23: Furniture | E23: Desk | F23: Emma Davis | G23: 7 | H23: 450 | I23: =G23*H23 -> 3150 | J23: 280
A24: 45359 | B24: =TEXT(A24,"mmm") -> Mar | C24: East | D24: Office Supplies | E24: Toner | F24: Carlos Lee | G24: 20 | H24: 85 | I24: =G24*H24 -> 1700 | J24: 42
A25: 45361 | B25: =TEXT(A25,"mmm") -> Mar | C25: West | D25: Electronics | E25: Tablet | F25: Sarah Chen | G25: 5 | H25: 550 | I25: =G25*H25 -> 2750 | J25: 380
A26: 45366 | B26: =TEXT(A26,"mmm") -> Mar | C26: North | D26: Furniture | E26: Chair | F26: John Smith | G26: 18 | H26: 180 | I26: =G26*H26 -> 3240 | J26: 95

Sheet Sales_Data
A1: Date | B1: Region | C1: Product_Category | D1: Product | E1: Sales_Rep | F1: Units_Sold | G1: Unit_Price | H1: Total_Revenue | I1: Cost_Per_Unit | J1: Profit | K1: Month | L1: Year | M1: Quarter | N1: ProfitMargin | O1: Sales_Rep_Info.Commission_Rate | P1: Commission-Amount | Q1: Totalrevenuebyregionandmonth | R1: Totalprofitbyproductcategoryandquarter | S1: Commission_Amount | T1: Target_Revenue | U1: Sales_CAtagory | V1: Flag/Thresold | AA1: Unique_Product | AB1: Revenue_per_product | AC1: Top_3_product&Amount_revenue | AF1: avg_profit_margin_per_product | AG1: Bottom_3_products_profit_margin
A2: 45296 | B2: North | C2: Electronics | D2: Laptop | E2: JohnSmith | F2: 5 | G2: 1200 | H2: 6000 | I2: 850 | J2: 1750 | K2: January | L2: 2024 | M2: ="Q"&ROUNDUP(MONTH(Sales_Data[[#This Row],[Date]])/3,0) -> Q1 | N2: 29 | O2: 0.08 | P2: 480 | Q2: =SUMIFS($H:$H,$B:$B,B2,$K:$K,K2) -> 16560 | R2: =SUMIFS($J:$J,$C:$C,C2,$M:$M,M2) -> 15100 | S2: =Sales_Data[[#This Row],[Total_Revenue]]*Sales_Data[[#This Row],[Sales_Rep_Info.Commission_Rate]] -> 480 | T2: =INDEX(Sales_Targets!$C:$C,MATCH(Sales_Data[[#This Row],[Product_Category]],Sales_Targets!$D:$D,0),MATCH(Sales_Data[[#Headers],[Target_Revenue]],Sales_Targets[[#Headers],[Target_Revenue]],0)) -> 15000 | U2: {=_xlfn.IFS(Sales_Data[[#This Row],[Total_Revenue]]>5000, "High",Sales_Data[[#This Row],[Total_Revenue]]>=1000, "Medium", Sales_Data[[#This Row],[Total_Revenue]]<1000, "Low")} -> High | V2: =IF(Sales_Data[[#This Row],[Target_Revenue]]/Sales_Data[[#This Row],[Total_Revenue]]>0.8, "Flag", "Thresold") -> Flag | AA2: {=_xlfn.UNIQUE(Sales_Data[Product])} -> Laptop | AB2: =SUMIFS(Sales_Data[Total_Revenue],Sales_Data[Product],AA2) -> 30000 | AC2: {=_xlfn.TAKE(_xlfn._xlws.SORT(AA2:AB11,2,-1),3)} -> Laptop | AD2: 30000 | AF2: =AVERAGEIFS(Sales_Data[ProfitMargin],Sales_Data[Product],AA2) -> 29 | AG2: {=_xlfn.TAKE(_xlfn._xlws.SORT(AA2:AB11,2,1),3)} -> Pens | AH2: 500
A3: 45299 | B3: South | C3: Furniture | D3: Desk | E3: EmmaDavis | F3: 3 | G3: 450 | H3: 1350 | I3: 280 | J3: 510 | K3: January | L3: 2024 | M3: ="Q"&ROUNDUP(MONTH(Sales_Data[[#This Row],[Date]])/3,0) -> Q1 | N3: 38 | O3: 0.09 | P3: 121.5 | Q3: =SUMIFS($H:$H,$B:$B,B3,$K:$K,K3) -> 5925 | R3: =SUMIFS($J:$J,$C:$C,C3,$M:$M,M3) -> 7725 | S3: =Sales_Data[[#This Row],[Total_Revenue]]*Sales_Data[[#This Row],[Sales_Rep_Info.Commission_Rate]] -> 121.5 | T3: =INDEX(Sales_Targets!$C:$C,MATCH(Sales_Data[[#This Row],[Product_Category]],Sales_Targets!$D:$D,0),MATCH(Sales_Data[[#Headers],[Target_Revenue]],Sales_Targets[[#Headers],[Target_Revenue]],0)) -> 8000 | U3: {=_xlfn.IFS(Sales_Data[[#This Row],[Total_Revenue]]>5000, "High",Sales_Data[[#This Row],[Total_Revenue]]>=1000, "Medium", Sales_Data[[#This Row],[Total_Revenue]]<1000, "Low")} -> Medium | V3: =IF(Sales_Data[[#This Row],[Target_Revenue]]/Sales_Data[[#This Row],[Total_Revenue]]>0.8, "Flag", "Thresold") -> Flag | AA3: Desk | AB3: =SUMIFS(Sales_Data[Total_Revenue],Sales_Data[Product],AA3) -> 6750 | AC3: Tablet | AD3: 10450 | AF3: =AVERAGEIFS(Sales_Data[ProfitMargin],Sales_Data[Product],AA3) -> 38 | AG3: Printer | AH3: 1960
A4: 45301 | B4: East | C4: Electronics | D4: Monitor | E4: CarlosLee | F4: 8 | G4: 350 | H4: 2800 | I4: 220 | J4: 1040 | K4: January | L4: 2024 | M4: ="Q"&ROUNDUP(MONTH(Sales_Data[[#This Row],[Date]])/3,0) -> Q1 | N4: 37 | O4: 0.07 | P4: 196 | Q4: =SUMIFS($H:$H,$B:$B,B4,$K:$K,K4) -> 4050 | R4: =SUMIFS($J:$J,$C:$C,C4,$M:$M,M4) -> 15100 | S4: =Sales_Data[[#This Row],[Total_Revenue]]*Sales_Data[[#This Row],[Sales_Rep_Info.Commission_Rate]] -> 196 | T4: =INDEX(Sales_Targets!$C:$C,MATCH(Sales_Data[[#This Row],[Product_Category]],Sales_Targets!$D:$D,0),MATCH(Sales_Data[[#Headers],[Target_Revenue]],Sales_Targets[[#Headers],[Target_Revenue]],0)) -> 15000 | U4: {=_xlfn.IFS(Sales_Data[[#This Row],[Total_Revenue]]>5000, "High",Sales_Data[[#This Row],[Total_Revenue]]>=1000, "Medium", Sales_Data[[#This Row],[Total_Revenue]]<1000, "Low")} -> Medium | V4: =IF(Sales_Data[[#This Row],[Target_Revenue]]/Sales_Data[[#This Row],[Total_Revenue]]>0.8, "Flag", "Thresold") -> Flag | AA4: Monitor | AB4: =SUMIFS(Sales_Data[Total_Revenue],Sales_Data[Product],AA4) -> 8400 | AC4: Monitor | AD4: 8400 | AF4: =AVERAGEIFS(Sales_Data[ProfitMargin],Sales_Data[Product],AA4) -> 37 | AG4: Paper | AH4: 2750
A5: 45303 | B5: West | C5: OfficeSupplies | D5: Printer | E5: SarahChen | F5: 4 | G5: 280 | H5: 1120 | I5: 180 | J5: 400 | K5: January | L5: 2024 | M5: ="Q"&ROUNDUP(MONTH(Sales_Data[[#This Row],[Date]])/3,0) -> Q1 | N5: 36 | O5: 0.08 | P5: 89.6 | Q5: =SUMIFS($H:$H,$B:$B,B5,$K:$K,K5) -> 2360 | R5: =SUMIFS($J:$J,$C:$C,C5,$M:$M,M5) -> 3935 | S5: =Sales_Data[[#This Row],[Total_Revenue]]*Sales_Data[[#This Row],[Sales_Rep_Info.Commission_Rate]] -> 89.6 | T5: =INDEX(Sales_Targets!$C:$C,MATCH(Sales_Data[[#This Row],[Product_Category]],Sales_Targets!$D:$D,0),MATCH(Sales_Data[[#Headers],[Target_Revenue]],Sales_Targets[[#Headers],[Target_Revenue]],0)) -> 3000 | U5: {=_xlfn.IFS(Sales_Data[[#This Row],[Total_Revenue]]>5000, "High",Sales_Data[[#This Row],[Total_Revenue]]>=1000, "Medium", Sales_Data[[#This Row],[Total_Revenue]]<1000, "Low")} -> Medium | V5: =IF(Sales_Data[[#This Row],[Target_Revenue]]/Sales_Data[[#This Row],[Total_Revenue]]>0.8, "Flag", "Thresold") -> Flag | AA5: Printer | AB5: =SUMIFS(Sales_Data[Total_Revenue],Sales_Data[Product],AA5) -> 1960 | AF5: =AVERAGEIFS(Sales_Data[ProfitMargin],Sales_Data[Product],AA5) -> 36
A6: 45306 | B6: North | C6: Furniture | D6: Chair | E6: JohnSmith | F6: 12 | G6: 180 | H6: 2160 | I6: 95 | J6: 1020 | K6: January | L6: 2024 | M6: ="Q"&ROUNDUP(MONTH(Sales_Data[[#This Row],[Date]])/3,0) -> Q1 | N6: 47 | O6: 0.08 | P6: 172.8 | Q6: =SUMIFS($H:$H,$B:$B,B6,$K:$K,K6) -> 16560 | R6: =SUMIFS($J:$J,$C:$C,C6,$M:$M,M6) -> 7725 | S6: =Sales_Data[[#This Row],[Total_Revenue]]*Sales_Data[[#This Row],[Sales_Rep_Info.Commission_Rate]] -> 172.8 | T6: =INDEX(Sales_Targets!$C:$C,MATCH(Sales_Data[[#This Row],[Product_Category]],Sales_Targets!$D:$D,0),MATCH(Sales_Data[[#Headers],[Target_Revenue]],Sales_Targets[[#Headers],[Target_Revenue]],0)) -> 8000 | U6: {=_xlfn.IFS(Sales_Data[[#This Row],[Total_Revenue]]>5000, "High",Sales_Data[[#This Row],[Total_Revenue]]>=1000, "Medium", Sales_Data[[#This Row],[Total_Revenue]]<1000, "Low")} -> Medium | V6: =IF(Sales_Data[[#This Row],[Target_Revenue]]/Sales_Data[[#This Row],[Total_Revenue]]>0.8, "Flag", "Thresold") -> Flag | AA6: Chair | AB6: =SUMIFS(Sales_Data[Total_Revenue],Sales_Data[Product],AA6) -> 8100 | AF6: =AVERAGEIFS(Sales_Data[ProfitMargin],Sales_Data[Product],AA6) -> 47
A7: 45309 | B7: South | C7: Electronics | D7: Tablet | E7: EmmaDavis | F7: 6 | G7: 550 | H7: 3300 | I7: 380 | J7: 1020 | K7: January | L7: 2024 | M7: ="Q"&ROUNDUP(MONTH(Sales_Data[[#This Row],[Date]])/3,0) -> Q1 | N7: 31 | O7: 0.09 | P7: 297 | Q7: =SUMIFS($H:$H,$B:$B,B7,$K:$K,K7) -> 5925 | R7: =SUMIFS($J:$J,$C:$C,C7,$M:$M,M7) -> 15100 | S7: =Sales_Data[[#This Row],[Total_Revenue]]*Sales_Data[[#This Row],[Sales_Rep_Info.Commission_Rate]] -> 297 | T7: =INDEX(Sales_Targets!$C:$C,MATCH(Sales_Data[[#This Row],[Product_Category]],Sales_Targets!$D:$D,0),MATCH(Sales_Data[[#Headers],[Target_Revenue]],Sales_Targets[[#Headers],[Target_Revenue]],0)) -> 15000 | U7: {=_xlfn.IFS(Sales_Data[[#This Row],[Total_Revenue]]>5000, "High",Sales_Data[[#This Row],[Total_Revenue]]>=1000, "Medium", Sales_Data[[#This Row],[Total_Revenue]]<1000, "Low")} -> Medium | V7: =IF(Sales_Data[[#This Row],[Target_Revenue]]/Sales_Data[[#This Row],[Total_Revenue]]>0.8, "Flag", "Thresold") -> Flag | AA7: Tablet | AB7: =SUMIFS(Sales_Data[Total_Revenue],Sales_Data[Product],AA7) -> 10450 | AF7: =AVERAGEIFS(Sales_Data[ProfitMargin],Sales_Data[Product],AA7) -> 31
A8: 45311 | B8: East | C8: OfficeSupplies | D8: Paper | E8: CarlosLee | F8: 50 | G8: 25 | H8: 1250 | I8: 12 | J8: 650 | K8: January | L8: 2024 | M8: ="Q"&ROUNDUP(MONTH(Sales_Data[[#This Row],[Date]])/3,0) -> Q1 | N8: 52 | O8: 0.07 | P8: 87.5 | Q8: =SUMIFS($H:$H,$B:$B,B8,$K:$K,K8) -> 4050 | R8: =SUMIFS($J:$J,$C:$C,C8,$M:$M,M8) -> 3935 | S8: =Sales_Data[[#This Row],[Total_Revenue]]*Sales_Data[[#This Row],[Sales_Rep_Info.Commission_Rate]] -> 87.5 | T8: =INDEX(Sales_Targets!$C:$C,MATCH(Sales_Data[[#This Row],[Product_Category]],Sales_Targets!$D:$D,0),MATCH(Sales_Data[[#Headers],[Target_Revenue]],Sales_Targets[[#Headers],[Target_Revenue]],0)) -> 3000 | U8: {=_xlfn.IFS(Sales_Data[[#This Row],[Total_Revenue]]>5000, "High",Sales_Data[[#This Row],[Total_Revenue]]>=1000, "Medium", Sales_Data[[#This Row],[Total_Revenue]]<1000, "Low")} -> Medium | V8: =IF(Sales_Data[[#This Row],[Target_Revenue]]/Sales_Data[[#This Row],[Total_Revenue]]>0.8, "Flag", "Thresold") -> Flag | AA8: Paper | AB8: =SUMIFS(Sales_Data[Total_Revenue],Sales_Data[Product],AA8) -> 2750 | AF8: =AVERAGEIFS(Sales_Data[ProfitMargin],Sales_Data[Product],AA8) -> 52
A9: 45313 | B9: West | C9: Furniture | D9: Cabinet | E9: SarahChen | F9: 2 | G9: 620 | H9: 1240 | I9: 395 | J9: 450 | K9: January | L9: 2024 | M9: ="Q"&ROUNDUP(MONTH(Sales_Data[[#This Row],[Date]])/3,0) -> Q1 | N9: 36 | O9: 0.08 | P9: 99.2 | Q9: =SUMIFS($H:$H,$B:$B,B9,$K:$K,K9) -> 2360 | R9: =SUMIFS($J:$J,$C:$C,C9,$M:$M,M9) -> 7725 | S9: =Sales_Data[[#This Row],[Total_Revenue]]*Sales_Data[[#This Row],[Sales_Rep_Info.Commission_Rate]] -> 99.2 | T9: =INDEX(Sales_Targets!$C:$C,MATCH(Sales_Data[[#This Row],[Product_Category]],Sales_Targets!$D:$D,0),MATCH(Sales_Data[[#Headers],[Target_Revenue]],Sales_Targets[[#Headers],[Target_Revenue]],0)) -> 8000 | U9: {=_xlfn.IFS(Sales_Data[[#This Row],[Total_Revenue]]>5000, "High",Sales_Data[[#This Row],[Total_Revenue]]>=1000, "Medium", Sales_Data[[#This Row],[Total_Revenue]]<1000, "Low")} -> Medium | V9: =IF(Sales_Data[[#This Row],[Target_Revenue]]/Sales_Data[[#This Row],[Total_Revenue]]>0.8, "Flag", "Thresold") -> Flag | AA9: Cabinet | AB9: =SUMIFS(Sales_Data[Total_Revenue],Sales_Data[Product],AA9) -> 3720 | AF9: =AVERAGEIFS(Sales_Data[ProfitMargin],Sales_Data[Product],AA9) -> 36
A10: 45316 | B10: North | C10: Electronics | D10: Laptop | E10: JohnSmith | F10: 7 | G10: 1200 | H10: 8400 | I10: 850 | J10: 2450 | K10: January | L10: 2024 | M10: ="Q"&ROUNDUP(MONTH(Sales_Data[[#This Row],[Date]])/3,0) -> Q1 | N10: 29 | O10: 0.08 | P10: 672 | Q10: =SUMIFS($H:$H,$B:$B,B10,$K:$K,K10) -> 16560 | R10: =SUMIFS($J:$J,$C:$C,C10,$M:$M,M10) -> 15100 | S10: =Sales_Data[[#This Row],[Total_Revenue]]*Sales_Data[[#This Row],[Sales_Rep_Info.Commission_Rate]] -> 672 | T10: =INDEX(Sales_Targets!$C:$C,MATCH(Sales_Data[[#This Row],[Product_Category]],Sales_Targets!$D:$D,0),MATCH(Sales_Data[[#Headers],[Target_Revenue]],Sales_Targets[[#Headers],[Target_Revenue]],0)) -> 15000 | U10: {=_xlfn.IFS(Sales_Data[[#This Row],[Total_Revenue]]>5000, "High",Sales_Data[[#This Row],[Total_Revenue]]>=1000, "Medium", Sales_Data[[#This Row],[Total_Revenue]]<1000, "Low")} -> High | V10: =IF(Sales_Data[[#This Row],[Target_Revenue]]/Sales_Data[[#This Row],[Total_Revenue]]>0.8, "Flag", "Thresold") -> Flag | AA10: Toner | AB10: =SUMIFS(Sales_Data[Total_Revenue],Sales_Data[Product],AA10) -> 2975 | AF10: =AVERAGEIFS(Sales_Data[ProfitMargin],Sales_Data[Product],AA10) -> 51
A11: 45319 | B11: South | C11: OfficeSupplies | D11: Toner | E11: EmmaDavis | F11: 15 | G11: 85 | H11: 1275 | I11: 42 | J11: 645 | K11: January | L11: 2024 | M11: ="Q"&ROUNDUP(MONTH(Sales_Data[[#This Row],[Date]])/3,0) -> Q1 | N11: 51 | O11: 0.09 | P11: 114.75 | Q11: =SUMIFS($H:$H,$B:$B,B11,$K:$K,K11) -> 5925 | R11: =SUMIFS($J:$J,$C:$C,C11,$M:$M,M11) -> 3935 | S11: =Sales_Data[[#This Row],[Total_Revenue]]*Sales_Data[[#This Row],[Sales_Rep_Info.Commission_Rate]] -> 114.75 | T11: =INDEX(Sales_Targets!$C:$C,MATCH(Sales_Data[[#This Row],[Product_Category]],Sales_Targets!$D:$D,0),MATCH(Sales_Data[[#Headers],[Target_Revenue]],Sales_Targets[[#Headers],[Target_Revenue]],0)) -> 3000 | U11: {=_xlfn.IFS(Sales_Data[[#This Row],[Total_Revenue]]>5000, "High",Sales_Data[[#This Row],[Total_Revenue]]>=1000, "Medium", Sales_Data[[#This Row],[Total_Revenue]]<1000, "Low")} -> Medium | V11: =IF(Sales_Data[[#This Row],[Target_Revenue]]/Sales_Data[[#This Row],[Total_Revenue]]>0.8, "Flag", "Thresold") -> Flag | AA11: Pens | AB11: =SUMIFS(Sales_Data[Total_Revenue],Sales_Data[Product],AA11) -> 500 | AF11: =AVERAGEIFS(Sales_Data[ProfitMargin],Sales_Data[Product],AA11) -> 60
A12: 45324 | B12: East | C12: Electronics | D12: Monitor | E12: CarlosLee | F12: 10 | G12: 350 | H12: 3500 | I12: 220 | J12: 1300 | K12: February | L12: 2024 | M12: ="Q"&ROUNDUP(MONTH(Sales_Data[[#This Row],[Date]])/3,0) -> Q1 | N12: 37 | O12: 0.07 | P12: 245 | Q12: =SUMIFS($H:$H,$B:$B,B12,$K:$K,K12) -> 8300 | R12: =SUMIFS($J:$J,$C:$C,C12,$M:$M,M12) -> 15100 | S12: =Sales_Data[[#This Row],[Total_Revenue]]*Sales_Data[[#This Row],[Sales_Rep_Info.Commission_Rate]] -> 245 | T12: =INDEX(Sales_Targets!$C:$C,MATCH(Sales_Data[[#This Row],[Product_Category]],Sales_Targets!$D:$D,0),MATCH(Sales_Data[[#Headers],[Target_Revenue]],Sales_Targets[[#Headers],[Target_Revenue]],0)) -> 15000 | U12: {=_xlfn.IFS(Sales_Data[[#This Row],[Total_Revenue]]>5000, "High",Sales_Data[[#This Row],[Total_Revenue]]>=1000, "Medium", Sales_Data[[#This Row],[Total_Revenue]]<1000, "Low")} -> Medium | V12: =IF(Sales_Data[[#This Row],[Target_Revenue]]/Sales_Data[[#This Row],[Total_Revenue]]>0.8, "Flag", "Thresold") -> Flag
A13: 45327 | B13: West | C13: Furniture | D13: Desk | E13: SarahChen | F13: 5 | G13: 450 | H13: 2250 | I13: 280 | J13: 850 | K13: February | L13: 2024 | M13: ="Q"&ROUNDUP(MONTH(Sales_Data[[#This Row],[Date]])/3,0) -> Q1 | N13: 38 | O13: 0.08 | P13: 180 | Q13: =SUMIFS($H:$H,$B:$B,B13,$K:$K,K13) -> 8150 | R13: =SUMIFS($J:$J,$C:$C,C13,$M:$M,M13) -> 7725 | S13: =Sales_Data[[#This Row],[Total_Revenue]]*Sales_Data[[#This Row],[Sales_Rep_Info.Commission_Rate]] -> 180 | T13: =INDEX(Sales_Targets!$C:$C,MATCH(Sales_Data[[#This Row],[Product_Category]],Sales_Targets!$D:$D,0),MATCH(Sales_Data[[#Headers],[Target_Revenue]],Sales_Targets[[#Headers],[Target_Revenue]],0)) -> 8000 | U13: {=_xlfn.IFS(Sales_Data[[#This Row],[Total_Revenue]]>5000, "High",Sales_Data[[#This Row],[Total_Revenue]]>=1000, "Medium", Sales_Data[[#This Row],[Total_Revenue]]<1000, "Low")} -> Medium | V13: =IF(Sales_Data[[#This Row],[Target_Revenue]]/Sales_Data[[#This Row],[Total_Revenue]]>0.8, "Flag", "Thresold") -> Flag
A14: 45330 | B14: North | C14: OfficeSupplies | D14: Pens | E14: JohnSmith | F14: 100 | G14: 5 | H14: 500 | I14: 2 | J14: 300 | K14: February | L14: 2024 | M14: ="Q"&ROUNDUP(MONTH(Sales_Data[[#This Row],[Date]])/3,0) -> Q1 | N14: 60 | O14: 0.08 | P14: 40 | Q14: =SUMIFS($H:$H,$B:$B,B14,$K:$K,K14) -> 1340 | R14: =SUMIFS($J:$J,$C:$C,C14,$M:$M,M14) -> 3935 | S14: =Sales_Data[[#This Row],[Total_Revenue]]*Sales_Data[[#This Row],[Sales_Rep_Info.Commission_Rate]] -> 40 | T14: =INDEX(Sales_Targets!$C:$C,MATCH(Sales_Data[[#This Row],[Product_Category]],Sales_Targets!$D:$D,0),MATCH(Sales_Data[[#Headers],[Target_Revenue]],Sales_Targets[[#Headers],[Target_Revenue]],0)) -> 3000 | U14: {=_xlfn.IFS(Sales_Data[[#This Row],[Total_Revenue]]>5000, "High",Sales_Data[[#This Row],[Total_Revenue]]>=1000, "Medium", Sales_Data[[#This Row],[Total_Revenue]]<1000, "Low")} -> Low | V14: =IF(Sales_Data[[#This Row],[Target_Revenue]]/Sales_Data[[#This Row],[Total_Revenue]]>0.8, "Flag", "Thresold") -> Flag
A15: 45332 | B15: South | C15: Electronics | D15: Laptop | E15: EmmaDavis | F15: 4 | G15: 1200 | H15: 4800 | I15: 850 | J15: 1400 | K15: February | L15: 2024 | M15: ="Q"&ROUNDUP(MONTH(Sales_Data[[#This Row],[Date]])/3,0) -> Q1 | N15: 29 | O15: 0.09 | P15: 432 | Q15: =SUMIFS($H:$H,$B:$B,B15,$K:$K,K15) -> 7280 | R15: =SUMIFS($J:$J,$C:$C,C15,$M:$M,M15) -> 15100 | S15: =Sales_Data[[#This Row],[Total_Revenue]]*Sales_Data[[#This Row],[Sales_Rep_Info.Commission_Rate]] -> 432 | T15: =INDEX(Sales_Targets!$C:$C,MATCH(Sales_Data[[#This Row],[Product_Category]],Sales_Targets!$D:$D,0),MATCH(Sales_Data[[#Headers],[Target_Revenue]],Sales_Targets[[#Headers],[Target_Revenue]],0)) -> 15000 | U15: {=_xlfn.IFS(Sales_Data[[#This Row],[Total_Revenue]]>5000, "High",Sales_Data[[#This Row],[Total_Revenue]]>=1000, "Medium", Sales_Data[[#This Row],[Total_Revenue]]<1000, "Low")} -> Medium | V15: =IF(Sales_Data[[#This Row],[Target_Revenue]]/Sales_Data[[#This Row],[Total_Revenue]]>0.8, "Flag", "Thresold") -> Flag
A16: 45334 | B16: East | C16: Furniture | D16: Chair | E16: CarlosLee | F16: 15 | G16: 180 | H16: 2700 | I16: 95 | J16: 1275 | K16: February | L16: 2024 | M16: ="Q"&ROUNDUP(MONTH(Sales_Data[[#This Row],[Date]])/3,0) -> Q1 | N16: 47 | O16: 0.07 | P16: 189 | Q16: =SUMIFS($H:$H,$B:$B,B16,$K:$K,K16) -> 8300 | R16: =SUMIFS($J:$J,$C:$C,C16,$M:$M,M16) -> 7725 | S16: =Sales_Data[[#This Row],[Total_Revenue]]*Sales_Data[[#This Row],[Sales_Rep_Info.Commission_Rate]] -> 189 | T16: =INDEX(Sales_Targets!$C:$C,MATCH(Sales_Data[[#This Row],[Product_Category]],Sales_Targets!$D:$D,0),MATCH(Sales_Data[[#Headers],[Target_Revenue]],Sales_Targets[[#Headers],[Target_Revenue]],0)) -> 8000 | U16: {=_xlfn.IFS(Sales_Data[[#This Row],[Total_Revenue]]>5000, "High",Sales_Data[[#This Row],[Total_Revenue]]>=1000, "Medium", Sales_Data[[#This Row],[Total_Revenue]]<1000, "Low")} -> Medium | V16: =IF(Sales_Data[[#This Row],[Target_Revenue]]/Sales_Data[[#This Row],[Total_Revenue]]>0.8, "Flag", "Thresold") -> Flag
A17: 45337 | B17: West | C17: Electronics | D17: Tablet | E17: SarahChen | F17: 8 | G17: 550 | H17: 4400 | I17: 380 | J17: 1360 | K17: February | L17: 2024 | M17: ="Q"&ROUNDUP(MONTH(Sales_Data[[#This Row],[Date]])/3,0) -> Q1 | N17: 31 | O17: 0.08 | P17: 352 | Q17: =SUMIFS($H:$H,$B:$B,B17,$K:$K,K17) -> 8150 | R17: =SUMIFS($J:$J,$C:$C,C17,$M:$M,M17) -> 15100 | S17: =Sales_Data[[#This Row],[Total_Revenue]]*Sales_Data[[#This Row],[Sales_Rep_Info.Commission_Rate]] -> 352 | T17: =INDEX(Sales_Targets!$C:$C,MATCH(Sales_Data[[#This Row],[Product_Category]],Sales_Targets!$D:$D,0),MATCH(Sales_Data[[#Headers],[Target_Revenue]],Sales_Targets[[#Headers],[Target_Revenue]],0)) -> 15000 | U17: {=_xlfn.IFS(Sales_Data[[#This Row],[Total_Revenue]]>5000, "High",Sales_Data[[#This Row],[Total_Revenue]]>=1000, "Medium", Sales_Data[[#This Row],[Total_Revenue]]<1000, "Low")} -> Medium | V17: =IF(Sales_Data[[#This Row],[Target_Revenue]]/Sales_Data[[#This Row],[Total_Revenue]]>0.8, "Flag", "Thresold") -> Flag
A18: 45340 | B18: North | C18: OfficeSupplies | D18: Printer | E18: JohnSmith | F18: 3 | G18: 280 | H18: 840 | I18: 180 | J18: 300 | K18: February | L18: 2024 | M18: ="Q"&ROUNDUP(MONTH(Sales_Data[[#This Row],[Date]])/3,0) -> Q1 | N18: 36 | O18: 0.08 | P18: 67.2 | Q18: =SUMIFS($H:$H,$B:$B,B18,$K:$K,K18) -> 1340 | R18: =SUMIFS($J:$J,$C:$C,C18,$M:$M,M18) -> 3935 | S18: =Sales_Data[[#This Row],[Total_Revenue]]*Sales_Data[[#This Row],[Sales_Rep_Info.Commission_Rate]] -> 67.2 | T18: =INDEX(Sales_Targets!$C:$C,MATCH(Sales_Data[[#This Row],[Product_Category]],Sales_Targets!$D:$D,0),MATCH(Sales_Data[[#Headers],[Target_Revenue]],Sales_Targets[[#Headers],[Target_Revenue]],0)) -> 3000 | U18: {=_xlfn.IFS(Sales_Data[[#This Row],[Total_Revenue]]>5000, "High",Sales_Data[[#This Row],[Total_Revenue]]>=1000, "Medium", Sales_Data[[#This Row],[Total_Revenue]]<1000, "Low")} -> Low | V18: =IF(Sales_Data[[#This Row],[Target_Revenue]]/Sales_Data[[#This Row],[Total_Revenue]]>0.8, "Flag", "Thresold") -> Flag
A19: 45342 | B19: South | C19: Furniture | D19: Cabinet | E19: EmmaDavis | F19: 4 | G19: 620 | H19: 2480 | I19: 395 | J19: 900 | K19: February | L19: 2024 | M19: ="Q"&ROUNDUP(MONTH(Sales_Data[[#This Row],[Date]])/3,0) -> Q1 | N19: 36 | O19: 0.09 | P19: 223.2 | Q19: =SUMIFS($H:$H,$B:$B,B19,$K:$K,K19) -> 7280 | R19: =SUMIFS($J:$J,$C:$C,C19,$M:$M,M19) -> 7725 | S19: =Sales_Data[[#This Row],[Total_Revenue]]*Sales_Data[[#This Row],[Sales_Rep_Info.Commission_Rate]] -> 223.2 | T19: =INDEX(Sales_Targets!$C:$C,MATCH(Sales_Data[[#This Row],[Product_Category]],Sales_Targets!$D:$D,0),MATCH(Sales_Data[[#Headers],[Target_Revenue]],Sales_Targets[[#Headers],[Target_Revenue]],0)) -> 8000 | U19: {=_xlfn.IFS(Sales_Data[[#This Row],[Total_Revenue]]>5000, "High",Sales_Data[[#This Row],[Total_Revenue]]>=1000, "Medium", Sales_Data[[#This Row],[Total_Revenue]]<1000, "Low")} -> Medium | V19: =IF(Sales_Data[[#This Row],[Target_Revenue]]/Sales_Data[[#This Row],[Total_Revenue]]>0.8, "Flag", "Thresold") -> Flag
A20: 45344 | B20: East | C20: Electronics | D20: Monitor | E20: CarlosLee | F20: 6 | G20: 350 | H20: 2100 | I20: 220 | J20: 780 | K20: February | L20: 2024 | M20: ="Q"&ROUNDUP(MONTH(Sales_Data[[#This Row],[Date]])/3,0) -> Q1 | N20: 37 | O20: 0.07 | P20: 147 | Q20: =SUMIFS($H:$H,$B:$B,B20,$K:$K,K20) -> 8300 | R20: =SUMIFS($J:$J,$C:$C,C20,$M:$M,M20) -> 15100 | S20: =Sales_Data[[#This Row],[Total_Revenue]]*Sales_Data[[#This Row],[Sales_Rep_Info.Commission_Rate]] -> 147 | T20: =INDEX(Sales_Targets!$C:$C,MATCH(Sales_Data[[#This Row],[Product_Category]],Sales_Targets!$D:$D,0),MATCH(Sales_Data[[#Headers],[Target_Revenue]],Sales_Targets[[#Headers],[Target_Revenue]],0)) -> 15000 | U20: {=_xlfn.IFS(Sales_Data[[#This Row],[Total_Revenue]]>5000, "High",Sales_Data[[#This Row],[Total_Revenue]]>=1000, "Medium", Sales_Data[[#This Row],[Total_Revenue]]<1000, "Low")} -> Medium | V20: =IF(Sales_Data[[#This Row],[Target_Revenue]]/Sales_Data[[#This Row],[Total_Revenue]]>0.8, "Flag", "Thresold") -> Flag
A21: 45347 | B21: West | C21: OfficeSupplies | D21: Paper | E21: SarahChen | F21: 60 | G21: 25 | H21: 1500 | I21: 12 | J21: 780 | K21: February | L21: 2024 | M21: ="Q"&ROUNDUP(MONTH(Sales_Data[[#This Row],[Date]])/3,0) -> Q1 | N21: 52 | O21: 0.08 | P21: 120 | Q21: =SUMIFS($H:$H,$B:$B,B21,$K:$K,K21) -> 8150 | R21: =SUMIFS($J:$J,$C:$C,C21,$M:$M,M21) -> 3935 | S21: =Sales_Data[[#This Row],[Total_Revenue]]*Sales_Data[[#This Row],[Sales_Rep_Info.Commission_Rate]] -> 120 | T21: =INDEX(Sales_Targets!$C:$C,MATCH(Sales_Data[[#This Row],[Product_Category]],Sales_Targets!$D:$D,0),MATCH(Sales_Data[[#Headers],[Target_Revenue]],Sales_Targets[[#Headers],[Target_Revenue]],0)) -> 3000 | U21: {=_xlfn.IFS(Sales_Data[[#This Row],[Total_Revenue]]>5000, "High",Sales_Data[[#This Row],[Total_Revenue]]>=1000, "Medium", Sales_Data[[#This Row],[Total_Revenue]]<1000, "Low")} -> Medium | V21: =IF(Sales_Data[[#This Row],[Target_Revenue]]/Sales_Data[[#This Row],[Total_Revenue]]>0.8, "Flag", "Thresold") -> Flag
A22: 45352 | B22: North | C22: Electronics | D22: Laptop | E22: JohnSmith | F22: 9 | G22: 1200 | H22: 10800 | I22: 850 | J22: 3150 | K22: March | L22: 2024 | M22: ="Q"&ROUNDUP(MONTH(Sales_Data[[#This Row],[Date]])/3,0) -> Q1 | N22: 29 | O22: 0.08 | P22: 864 | Q22: =SUMIFS($H:$H,$B:$B,B22,$K:$K,K22) -> 14040 | R22: =SUMIFS($J:$J,$C:$C,C22,$M:$M,M22) -> 15100 | S22: =Sales_Data[[#This Row],[Total_Revenue]]*Sales_Data[[#This Row],[Sales_Rep_Info.Commission_Rate]] -> 864 | T22: =INDEX(Sales_Targets!$C:$C,MATCH(Sales_Data[[#This Row],[Product_Category]],Sales_Targets!$D:$D,0),MATCH(Sales_Data[[#Headers],[Target_Revenue]],Sales_Targets[[#Headers],[Target_Revenue]],0)) -> 15000 | U22: {=_xlfn.IFS(Sales_Data[[#This Row],[Total_Revenue]]>5000, "High",Sales_Data[[#This Row],[Total_Revenue]]>=1000, "Medium", Sales_Data[[#This Row],[Total_Revenue]]<1000, "Low")} -> High | V22: =IF(Sales_Data[[#This Row],[Target_Revenue]]/Sales_Data[[#This Row],[Total_Revenue]]>0.8, "Flag", "Thresold") -> Flag
A23: 45356 | B23: South | C23: Furniture | D23: Desk | E23: EmmaDavis | F23: 7 | G23: 450 | H23: 3150 | I23: 280 | J23: 1190 | K23: March | L23: 2024 | M23: ="Q"&ROUNDUP(MONTH(Sales_Data[[#This Row],[Date]])/3,0) -> Q1 | N23: 38 | O23: 0.09 | P23: 283.5 | Q23: =SUMIFS($H:$H,$B:$B,B23,$K:$K,K23) -> 3150 | R23: =SUMIFS($J:$J,$C:$C,C23,$M:$M,M23) -> 7725 | S23: =Sales_Data[[#This Row],[Total_Revenue]]*Sales_Data[[#This Row],[Sales_Rep_Info.Commission_Rate]] -> 283.5 | T23: =INDEX(Sales_Targets!$C:$C,MATCH(Sales_Data[[#This Row],[Product_Category]],Sales_Targets!$D:$D,0),MATCH(Sales_Data[[#Headers],[Target_Revenue]],Sales_Targets[[#Headers],[Target_Revenue]],0)) -> 8000 | U23: {=_xlfn.IFS(Sales_Data[[#This Row],[Total_Revenue]]>5000, "High",Sales_Data[[#This Row],[Total_Revenue]]>=1000, "Medium", Sales_Data[[#This Row],[Total_Revenue]]<1000, "Low")} -> Medium | V23: =IF(Sales_Data[[#This Row],[Target_Revenue]]/Sales_Data[[#This Row],[Total_Revenue]]>0.8, "Flag", "Thresold") -> Flag
... A26: 45366 | B26: North | C26: Furniture | D26: Chair | E26: JohnSmith | F26: 18 | G26: 180 | H26: 3240 | I26: 95 | J26: 1530 | K26: March | L26: 2024 | M26: ="Q"&ROUNDUP(MONTH(Sales_Data[[#This Row],[Date]])/3,0) -> Q1 | N26: 47 | O26: 0.08 | P26: 259.2 | Q26: =SUMIFS($H:$H,$B:$B,B26,$K:$K,K26) -> 14040 | R26: =SUMIFS($J:$J,$C:$C,C26,$M:$M,M26) -> 7725 | S26: =Sales_Data[[#This Row],[Total_Revenue]]*Sales_Data[[#This Row],[Sales_Rep_Info.Commission_Rate]] -> 259.2 | T26: =INDEX(Sales_Targets!$C:$C,MATCH(Sales_Data[[#This Row],[Product_Category]],Sales_Targets!$D:$D,0),MATCH(Sales_Data[[#Headers],[Target_Revenue]],Sales_Targets[[#Headers],[Target_Revenue]],0)) -> 8000 | U26: {=_xlfn.IFS(Sales_Data[[#This Row],[Total_Revenue]]>5000, "High",Sales_Data[[#This Row],[Total_Revenue]]>=1000, "Medium", Sales_Data[[#This Row],[Total_Revenue]]<1000, "Low")} -> Medium | V26: =IF(Sales_Data[[#This Row],[Target_Revenue]]/Sales_Data[[#This Row],[Total_Revenue]]>0.8, "Flag", "Thresold") -> Flag
Q1048576: =SUM(Q2:Q1048575) -> 182545 | AF1048576: =SUM(AF2:AF1048575) -> 417

Sheet Executive Summary
A1: EXECUTIVE SUMMARY
A3: Key Findings | B3: ="Total Revenue is: "&TEXT(SUM(Sales_Data!H:H),"#,##0") -> Total Revenue is: 75,605
B4: ="Highest Revenue Month: "&INDEX(Sales_Data[Month],MATCH(MAX(Sales_Data[Total_Revenue]),Sales_Data[Total_Revenue],0)) -> Highest Revenue Month: March
B5: ="Average Profit Margin: "&ROUND(AVERAGE(Sales_Data[ProfitMargin]),2)&"%" -> Average Profit Margin: 39.4%
A7: Recommendations | B7: =IF(MAX(Sales_Data[Total_Revenue])>10000,"Product is nice and should marketing to increase revenue more. The revenue is "&MAX(Sales_Data[Total_Revenue])) -> Product is nice and should marketing to increase revenue more. The revenue is 10800
A10: Performance Trends
A13: Risk Areas | B13: ="Averrage profit Margin: "&ROUND(AVERAGE(Sales_Data[ProfitMargin]),2)&"%.""So, Profit margin is 'Low'." -> Averrage profit Margin: 39.4%."So, Profit margin is 'Low'.
B14: ="Lowest Performing Region: "&INDEX(Sales_Data[Region],MATCH(MIN(Sales_Data[Total_Revenue]),Sales_Data[Total_Revenue],0)) -> Lowest Performing Region: North
A23: Opportunities
